{
  "scan_date": "2026-06-29T22:49:51.427248",
  "total_attempted": 3761,
  "total_scanned": 3173,
  "candidates_7_plus": 891,
  "candidates_all_8": 491,
  "sweet_spot_count": 399,
  "top_candidates": [
    {
      "ticker": "HG",
      "price": 34.13,
      "pct_from_high": 0.0,
      "rs_rating": 95,
      "stock_return_1y": 123.6,
      "criteria_passed": 8,
      "all_criteria_met": true,
      "composite": 94
    },
    {
      "ticker": "SN",
      "price": 146.38,
      "pct_from_high": -0.0,
      "rs_rating": 95,
      "stock_return_1y": 89.7,
      "criteria_passed": 8,
      "all_criteria_met": true,
      "composite": 93
    },
    {
      "ticker": "MSGS",
      "price": 403.03,
      "pct_from_high": 0.0,
      "rs_rating": 95,
      "stock_return_1y": 109.5,
      "criteria_passed": 8,
      "all_criteria_met": true,
      "composite": 94
    },
    {
      "ticker": "USFD",
      "price": 102.44,
      "pct_from_high": -0.0,
      "rs_rating": 95,
      "stock_return_1y": 94.9,
      "criteria_passed": 8,
      "all_criteria_met": true,
      "composite": 93
    },
    {
      "ticker": "CSGS",
      "price": 80.69,
      "pct_from_high": -0.0,
      "rs_rating": 95,
      "stock_return_1y": 106.5,
      "criteria_passed": 8,
      "all_criteria_met": true,
      "composite": 94
    },
    {
      "ticker": "KALV",
      "price": 27.0,
      "pct_from_high": 0.0,
      "rs_rating": 95,
      "stock_return_1y": 127.1,
      "criteria_passed": 8,
      "all_criteria_met": true,
      "composite": 95
    },
    {
      "ticker": "TDAY",
      "price": 8.65,
      "pct_from_high": 0.0,
      "rs_rating": 85,
      "stock_return_1y": 84.4,
      "criteria_passed": 8,
      "all_criteria_met": true,
      "composite": 89
    },
    {
      "ticker": "TRV",
      "price": 331.88,
      "pct_from_high": -0.0,
      "rs_rating": 75,
      "stock_return_1y": 68.9,
      "criteria_passed": 8,
      "all_criteria_met": true,
      "composite": 85
    },
    {
      "ticker": "PRA",
      "price": 25.0,
      "pct_from_high": -0.1,
      "rs_rating": 95,
      "stock_return_1y": 104.9,
      "criteria_passed": 8,
      "all_criteria_met": true,
      "composite": 93
    },
    {
      "ticker": "KRYS",
      "price": 378.15,
      "pct_from_high": -0.1,
      "rs_rating": 95,
      "stock_return_1y": 107.5,
      "criteria_passed": 8,
      "all_criteria_met": true,
      "composite": 94
    },
    {
      "ticker": "ECPG",
      "price": 92.82,
      "pct_from_high": -0.1,
      "rs_rating": 95,
      "stock_return_1y": 122.7,
      "criteria_passed": 8,
      "all_criteria_met": true,
      "composite": 94
    },
    {
      "ticker": "RY",
      "price": 204.79,
      "pct_from_high": -0.1,
      "rs_rating": 95,
      "stock_return_1y": 103.2,
      "criteria_passed": 8,
      "all_criteria_met": true,
      "composite": 93
    },
    {
      "ticker": "RPRX",
      "price": 57.09,
      "pct_from_high": -0.1,
      "rs_rating": 95,
      "stock_return_1y": 129.3,
      "criteria_passed": 8,
      "all_criteria_met": true,
      "composite": 95
    },
    {
      "ticker": "MO",
      "price": 74.05,
      "pct_from_high": -0.1,
      "rs_rating": 85,
      "stock_return_1y": 84.9,
      "criteria_passed": 8,
      "all_criteria_met": true,
      "composite": 89
    },
    {
      "ticker": "WBS",
      "price": 76.02,
      "pct_from_high": -0.1,
      "rs_rating": 85,
      "stock_return_1y": 81.6,
      "criteria_passed": 8,
      "all_criteria_met": true,
      "composite": 89
    },
    {
      "ticker": "THG",
      "price": 214.54,
      "pct_from_high": -0.1,
      "rs_rating": 85,
      "stock_return_1y": 79.2,
      "criteria_passed": 8,
      "all_criteria_met": true,
      "composite": 89
    },
    {
      "ticker": "ARMK",
      "price": 56.23,
      "pct_from_high": -0.1,
      "rs_rating": 85,
      "stock_return_1y": 72.7,
      "criteria_passed": 8,
      "all_criteria_met": true,
      "composite": 88
    },
    {
      "ticker": "NUVL",
      "price": 123.51,
      "pct_from_high": -0.1,
      "rs_rating": 75,
      "stock_return_1y": 63.6,
      "criteria_passed": 8,
      "all_criteria_met": true,
      "composite": 84
    },
    {
      "ticker": "CYTK",
      "price": 87.26,
      "pct_from_high": -0.1,
      "rs_rating": 75,
      "stock_return_1y": 59.5,
      "criteria_passed": 8,
      "all_criteria_met": true,
      "composite": 84
    },
    {
      "ticker": "WSR",
      "price": 18.96,
      "pct_from_high": -0.1,
      "rs_rating": 75,
      "stock_return_1y": 55.6,
      "criteria_passed": 8,
      "all_criteria_met": true,
      "composite": 84
    },
    {
      "ticker": "FBNC",
      "price": 64.05,
      "pct_from_high": -0.2,
      "rs_rating": 95,
      "stock_return_1y": 109.4,
      "criteria_passed": 8,
      "all_criteria_met": true,
      "composite": 94
    },
    {
      "ticker": "PKBK",
      "price": 33.19,
      "pct_from_high": -0.2,
      "rs_rating": 95,
      "stock_return_1y": 117.7,
      "criteria_passed": 8,
      "all_criteria_met": true,
      "composite": 94
    },
    {
      "ticker": "BMO",
      "price": 176.08,
      "pct_from_high": -0.2,
      "rs_rating": 95,
      "stock_return_1y": 126.3,
      "criteria_passed": 8,
      "all_criteria_met": true,
      "composite": 94
    },
    {
      "ticker": "MNST",
      "price": 97.64,
      "pct_from_high": -0.2,
      "rs_rating": 95,
      "stock_return_1y": 95.7,
      "criteria_passed": 8,
      "all_criteria_met": true,
      "composite": 93
    },
    {
      "ticker": "HCSG",
      "price": 24.5,
      "pct_from_high": -0.2,
      "rs_rating": 95,
      "stock_return_1y": 125.0,
      "criteria_passed": 8,
      "all_criteria_met": true,
      "composite": 94
    },
    {
      "ticker": "PANW",
      "price": 332.0,
      "pct_from_high": -0.2,
      "rs_rating": 95,
      "stock_return_1y": 94.8,
      "criteria_passed": 7,
      "all_criteria_met": false,
      "composite": 88
    },
    {
      "ticker": "ALL",
      "price": 241.38,
      "pct_from_high": -0.2,
      "rs_rating": 75,
      "stock_return_1y": 56.3,
      "criteria_passed": 8,
      "all_criteria_met": true,
      "composite": 84
    },
    {
      "ticker": "TRIN",
      "price": 17.73,
      "pct_from_high": -0.2,
      "rs_rating": 75,
      "stock_return_1y": 65.8,
      "criteria_passed": 8,
      "all_criteria_met": true,
      "composite": 84
    },
    {
      "ticker": "FFBC",
      "price": 33.9,
      "pct_from_high": -0.2,
      "rs_rating": 75,
      "stock_return_1y": 64.6,
      "criteria_passed": 8,
      "all_criteria_met": true,
      "composite": 84
    },
    {
      "ticker": "LNT",
      "price": 77.18,
      "pct_from_high": -0.2,
      "rs_rating": 75,
      "stock_return_1y": 62.2,
      "criteria_passed": 8,
      "all_criteria_met": true,
      "composite": 84
    },
    {
      "ticker": "SXI",
      "price": 355.03,
      "pct_from_high": -0.3,
      "rs_rating": 95,
      "stock_return_1y": 129.5,
      "criteria_passed": 8,
      "all_criteria_met": true,
      "composite": 95
    },
    {
      "ticker": "FROG",
      "price": 90.09,
      "pct_from_high": -0.3,
      "rs_rating": 95,
      "stock_return_1y": 140.7,
      "criteria_passed": 8,
      "all_criteria_met": true,
      "composite": 95
    },
    {
      "ticker": "ALRS",
      "price": 31.03,
      "pct_from_high": -0.3,
      "rs_rating": 85,
      "stock_return_1y": 73.0,
      "criteria_passed": 8,
      "all_criteria_met": true,
      "composite": 88
    },
    {
      "ticker": "MTB",
      "price": 239.2,
      "pct_from_high": -0.3,
      "rs_rating": 85,
      "stock_return_1y": 69.2,
      "criteria_passed": 8,
      "all_criteria_met": true,
      "composite": 88
    },
    {
      "ticker": "WSBF",
      "price": 20.6,
      "pct_from_high": -0.3,
      "rs_rating": 85,
      "stock_return_1y": 73.9,
      "criteria_passed": 8,
      "all_criteria_met": true,
      "composite": 88
    },
    {
      "ticker": "BY",
      "price": 37.61,
      "pct_from_high": -0.3,
      "rs_rating": 75,
      "stock_return_1y": 62.5,
      "criteria_passed": 8,
      "all_criteria_met": true,
      "composite": 84
    },
    {
      "ticker": "FDSB",
      "price": 16.19,
      "pct_from_high": -0.3,
      "rs_rating": 75,
      "stock_return_1y": 58.0,
      "criteria_passed": 8,
      "all_criteria_met": true,
      "composite": 84
    },
    {
      "ticker": "FITB",
      "price": 56.78,
      "pct_from_high": -0.3,
      "rs_rating": 75,
      "stock_return_1y": 66.6,
      "criteria_passed": 8,
      "all_criteria_met": true,
      "composite": 84
    },
    {
      "ticker": "TFSL",
      "price": 17.53,
      "pct_from_high": -0.3,
      "rs_rating": 75,
      "stock_return_1y": 65.5,
      "criteria_passed": 8,
      "all_criteria_met": true,
      "composite": 84
    },
    {
      "ticker": "AIZ",
      "price": 267.98,
      "pct_from_high": -0.3,
      "rs_rating": 75,
      "stock_return_1y": 65.5,
      "criteria_passed": 8,
      "all_criteria_met": true,
      "composite": 84
    },
    {
      "ticker": "WELL",
      "price": 227.73,
      "pct_from_high": -0.4,
      "rs_rating": 95,
      "stock_return_1y": 126.8,
      "criteria_passed": 8,
      "all_criteria_met": true,
      "composite": 94
    },
    {
      "ticker": "RBCAA",
      "price": 90.3,
      "pct_from_high": -0.4,
      "rs_rating": 85,
      "stock_return_1y": 79.5,
      "criteria_passed": 8,
      "all_criteria_met": true,
      "composite": 88
    },
    {
      "ticker": "SPG",
      "price": 227.56,
      "pct_from_high": -0.4,
      "rs_rating": 85,
      "stock_return_1y": 70.9,
      "criteria_passed": 8,
      "all_criteria_met": true,
      "composite": 88
    },
    {
      "ticker": "GNW",
      "price": 9.52,
      "pct_from_high": -0.4,
      "rs_rating": 75,
      "stock_return_1y": 57.1,
      "criteria_passed": 8,
      "all_criteria_met": true,
      "composite": 84
    },
    {
      "ticker": "FIBK",
      "price": 38.59,
      "pct_from_high": -0.4,
      "rs_rating": 75,
      "stock_return_1y": 58.6,
      "criteria_passed": 8,
      "all_criteria_met": true,
      "composite": 84
    },
    {
      "ticker": "FRAF",
      "price": 64.0,
      "pct_from_high": -0.5,
      "rs_rating": 95,
      "stock_return_1y": 141.6,
      "criteria_passed": 8,
      "all_criteria_met": true,
      "composite": 95
    },
    {
      "ticker": "TD",
      "price": 120.33,
      "pct_from_high": -0.5,
      "rs_rating": 95,
      "stock_return_1y": 136.6,
      "criteria_passed": 8,
      "all_criteria_met": true,
      "composite": 95
    },
    {
      "ticker": "LYV",
      "price": 182.56,
      "pct_from_high": -0.5,
      "rs_rating": 95,
      "stock_return_1y": 92.6,
      "criteria_passed": 8,
      "all_criteria_met": true,
      "composite": 93
    },
    {
      "ticker": "NHC",
      "price": 206.33,
      "pct_from_high": -0.5,
      "rs_rating": 95,
      "stock_return_1y": 95.6,
      "criteria_passed": 8,
      "all_criteria_met": true,
      "composite": 93
    },
    {
      "ticker": "ZION",
      "price": 69.52,
      "pct_from_high": -0.5,
      "rs_rating": 85,
      "stock_return_1y": 71.2,
      "criteria_passed": 8,
      "all_criteria_met": true,
      "composite": 88
    }
  ]
}