{
  "scan_date": "2026-07-15T23:03:40.412812",
  "total_scanned": 3761,
  "signals_found": 8,
  "signals": [
    {
      "ticker": "STIM",
      "price": 1.840000033378601,
      "smma15": 1.492014807968,
      "smma29": 1.4682756944702906,
      "rsi": 65.42351634943385,
      "volume_surge": false
    },
    {
      "ticker": "NEOG",
      "price": 9.979999542236328,
      "smma15": 9.351512971419238,
      "smma29": 9.311581591516088,
      "rsi": 58.88582505483197,
      "volume_surge": false
    },
    {
      "ticker": "IVR",
      "price": 8.140000343322754,
      "smma15": 7.888370277529505,
      "smma29": 7.86770577922256,
      "rsi": 59.77659267962887,
      "volume_surge": false
    },
    {
      "ticker": "JXN",
      "price": 124.2699966430664,
      "smma15": 110.65564096305364,
      "smma29": 109.32330578480753,
      "rsi": 69.72752309160336,
      "volume_surge": false
    },
    {
      "ticker": "ALIT",
      "price": 21.75,
      "smma15": 16.23293010447876,
      "smma29": 15.904643036755804,
      "rsi": 65.54746795512469,
      "volume_surge": false
    },
    {
      "ticker": "BX",
      "price": 127.05000305175781,
      "smma15": 120.76265185390176,
      "smma29": 120.35299017662489,
      "rsi": 57.56249216670293,
      "volume_surge": false
    },
    {
      "ticker": "AMZN",
      "price": 254.9600067138672,
      "smma15": 245.73533661385957,
      "smma29": 245.60831018638714,
      "rsi": 56.29026747522024,
      "volume_surge": false
    },
    {
      "ticker": "META",
      "price": 681.3099975585938,
      "smma15": 610.3195991803932,
      "smma29": 609.9269779764628,
      "rsi": 62.865127123585566,
      "volume_surge": false
    }
  ]
}